joinery/__init__.py
joinery/cli.py
joinery/exceptions.py
joinery/op.py
joinery/api/__init__.py
joinery/api/base.py
joinery/api/openai.py
joinery/tests/__init__.py
joinery/tests/test_e2e.py
tts_joinery-1.0.5.dist-info/licenses/LICENSE
tts_joinery-1.0.5.dist-info/METADATA
tts_joinery-1.0.5.dist-info/WHEEL
tts_joinery-1.0.5.dist-info/entry_points.txt
tts_joinery-1.0.5.dist-info/top_level.txt
tts_joinery-1.0.5.dist-info/RECORD
