Metadata-Version: 2.4
Name: tts-joinery
Version: 1.0.5
Summary: Automate chunking long texts to produce a single audio file from text-to-speech APIs
Author-email: Adrien Delessert <adrien@delessert.com>
License: MIT License
Project-URL: Homepage, https://github.com/drien/tts-joinery
Keywords: openai,tts,ai,cli
Classifier: Programming Language :: Python :: 3
Requires-Python: >=3.8
License-File: LICENSE
Requires-Dist: click
Requires-Dist: nltk>=3.8.2
Requires-Dist: openai>=1.67.0
Requires-Dist: pip-tools
Requires-Dist: platformdirs
Requires-Dist: pydub
Requires-Dist: python-dotenv
Provides-Extra: test
Requires-Dist: pytest; extra == "test"
Dynamic: license-file
